README.md
setup.cfg
setup.py
generated_swagger_client.egg-info/PKG-INFO
generated_swagger_client.egg-info/SOURCES.txt
generated_swagger_client.egg-info/dependency_links.txt
generated_swagger_client.egg-info/requires.txt
generated_swagger_client.egg-info/top_level.txt
swagger_client/__init__.py
swagger_client/api_client.py
swagger_client/configuration.py
swagger_client/rest.py
swagger_client/api/__init__.py
swagger_client/api/custom_speech_accuracy_tests_api.py
swagger_client/api/custom_speech_datasets_for_model_adaptation_api.py
swagger_client/api/custom_speech_endpoints_api.py
swagger_client/api/custom_speech_models_api.py
swagger_client/api/custom_speech_transcriptions_api.py
swagger_client/api/service_health_api.py
swagger_client/api/voice_datasets_api.py
swagger_client/api/voice_endpoints_api.py
swagger_client/api/voice_models_api.py
swagger_client/api/voice_tests_api.py
swagger_client/models/__init__.py
swagger_client/models/component.py
swagger_client/models/dataset.py
swagger_client/models/dataset_definition.py
swagger_client/models/dataset_identity.py
swagger_client/models/dataset_update.py
swagger_client/models/endpoint.py
swagger_client/models/endpoint_data.py
swagger_client/models/endpoint_data_definition.py
swagger_client/models/endpoint_definition.py
swagger_client/models/endpoint_metadata_update.py
swagger_client/models/error_content.py
swagger_client/models/error_detail.py
swagger_client/models/health_status_response.py
swagger_client/models/i_read_only_dictionary2.py
swagger_client/models/inner_error_v2.py
swagger_client/models/model.py
swagger_client/models/model_definition.py
swagger_client/models/model_identity.py
swagger_client/models/model_training_locales.py
swagger_client/models/model_update.py
swagger_client/models/speech_endpoint_definition.py
swagger_client/models/speech_model_definition.py
swagger_client/models/test.py
swagger_client/models/test_definition.py
swagger_client/models/test_update.py
swagger_client/models/transcription.py
swagger_client/models/transcription_definition.py
swagger_client/models/transcription_update.py
swagger_client/models/voice_dataset.py
swagger_client/models/voice_model_v2.py
swagger_client/models/voice_test.py
