Metadata-Version: 1.1
Name: generated-swagger-client
Version: 1.0.2
Summary: Speech Services API v2.0
Home-page: UNKNOWN
Author: UNKNOWN
Author-email: UNKNOWN
License: UNKNOWN
Download-URL: https://github.com/networthdata/generated-swagger-client/archive/v1.0.1.tar.gz
Keywords: Swagger,Speech Services API v2.0
Platform: UNKNOWN
